stapax/__init__.py
stapax/cli.py
stapax/config.py
stapax/main.py
stapax/model_wrapper.py
stapax/types.py
stapax/callbacks/__init__.py
stapax/callbacks/save_test_output.py
stapax/configs/main.yaml
stapax/configs/dataset/mnist_seq.yaml
stapax/configs/experiment/base/mnist.yaml
stapax/configs/experiment/linoss/mnist.yaml
stapax/configs/model/encoder/identity.yaml
stapax/configs/model/encoder/linoss_encoder.yaml
stapax/configs/model/encoder/sequence_mixer/linoss.yaml
stapax/configs/model/heads/classification.yaml
stapax/configs/model/heads/multiclass.yaml
stapax/configs/model/heads/regression.yaml
stapax/dataset/__init__.py
stapax/dataset/mnist_seq.py
stapax/dataset/store.py
stapax/dataset/types.py
stapax/dataset/util.py
stapax/logging/__init__.py
stapax/logging/local_logger.py
stapax/loss/__init__.py
stapax/loss/cross_entropy.py
stapax/loss/gated_regression.py
stapax/loss/get_loss_fns.py
stapax/loss/mse.py
stapax/loss/store.py
stapax/loss/types.py
stapax/metric/__init__.py
stapax/metric/metrics.py
stapax/metric/types.py
stapax/misc/early_stopping.py
stapax/misc/learning_rate.py
stapax/misc/load_model.py
stapax/misc/save_checkpoint.py
stapax/misc/step_tracker.py
stapax/misc/stores.py
stapax/misc/util.py
stapax/models/__init__.py
stapax/models/model.py
stapax/models/encoder/__init__.py
stapax/models/encoder/identity.py
stapax/models/encoder/linoss_encoder.py
stapax/models/encoder/store.py
stapax/models/encoder/types.py
stapax/models/heads/__init__.py
stapax/models/heads/classification.py
stapax/models/heads/multiclass.py
stapax/models/heads/regression.py
stapax/models/heads/store.py
stapax/models/heads/types.py
stapax/models/sequence_mixer/__init__.py
stapax/models/sequence_mixer/linoss.py
stapax/models/sequence_mixer/store.py
stapax/models/sequence_mixer/types.py
stapax/optimizer/__init__.py
stapax/optimizer/learning_rate.py
stapax-0.1.7.dist-info/METADATA
stapax-0.1.7.dist-info/WHEEL
stapax-0.1.7.dist-info/entry_points.txt
stapax-0.1.7.dist-info/licenses/LICENSE
stapax-0.1.7.dist-info/RECORD
